oskat/.DS_Store
oskat/__init__.py
oskat/cli.py
oskat-0.1.2.dist-info/LICENSE
oskat-0.1.2.dist-info/METADATA
oskat-0.1.2.dist-info/WHEEL
oskat-0.1.2.dist-info/entry_points.txt
oskat-0.1.2.dist-info/RECORD
