Metadata-Version: 2.1
Name: oskat
Version: 0.1.2
Summary: Open-Source Kamera-Arts Tools
Author: Kevin Lao
Author-email: kevinlao.819@gmail.com
Requires-Python: >=3.9,<4.0
Classifier: Programming Language :: Python :: 3
Classifier: Programming Language :: Python :: 3.9
Classifier: Programming Language :: Python :: 3.10
Classifier: Programming Language :: Python :: 3.11
Classifier: Programming Language :: Python :: 3.12
Requires-Dist: click (>=8.1.7,<9.0.0)
Requires-Dist: opencv-python (>=4.9.0.80,<5.0.0.0)
